{
    "condition": "any_of",
    "terms": [
        {
            "condition": "entity_properties",
            "entity": "this",
            "predicate": {
                "location": {
                    "block": {
                        "blocks": [
                            "snow"
                        ],
                        "state": {
                            "layers": "2"
                        }
                    }
                },
                "distance": {
                    "y": {
                        "min": 0.0,
                        "max": 0.12499999990
                    }
                }
            }
        },
        {
            "condition": "entity_properties",
            "entity": "this",
            "predicate": {
                "location": {
                    "block": {
                        "blocks": [
                            "snow"
                        ],
                        "state": {
                            "layers": "3"
                        }
                    }
                },
                "distance": {
                    "y": {
                        "min": 0.0,
                        "max": 0.2499999990
                    }
                }
            }
        },
        {
            "condition": "entity_properties",
            "entity": "this",
            "predicate": {
                "location": {
                    "block": {
                        "blocks": [
                            "snow"
                        ],
                        "state": {
                            "layers": "4"
                        }
                    }
                },
                "distance": {
                    "y": {
                        "min": 0.0,
                        "max": 0.37499999990
                    }
                }
            }
        },
        {
            "condition": "entity_properties",
            "entity": "this",
            "predicate": {
                "location": {
                    "block": {
                        "blocks": [
                            "snow"
                        ],
                        "state": {
                            "layers": "5"
                        }
                    }
                },
                "distance": {
                    "y": {
                        "min": 0.0,
                        "max": 0.499999990
                    }
                }
            }
        },
        {
            "condition": "entity_properties",
            "entity": "this",
            "predicate": {
                "location": {
                    "block": {
                        "blocks": [
                            "snow"
                        ],
                        "state": {
                            "layers": "6"
                        }
                    }
                },
                "distance": {
                    "y": {
                        "min": 0.0,
                        "max": 0.62499999990
                    }
                }
            }
        },
        {
            "condition": "entity_properties",
            "entity": "this",
            "predicate": {
                "location": {
                    "block": {
                        "blocks": [
                            "snow"
                        ],
                        "state": {
                            "layers": "7"
                        }
                    }
                },
                "distance": {
                    "y": {
                        "min": 0.0,
                        "max": 0.7499999990
                    }
                }
            }
        },
        {
            "condition": "entity_properties",
            "entity": "this",
            "predicate": {
                "location": {
                    "block": {
                        "blocks": [
                            "snow"
                        ],
                        "state": {
                            "layers": "8"
                        }
                    }
                },
                "distance": {
                    "y": {
                        "min": 0.0,
                        "max": 0.87499999990
                    }
                }
            }
        }
    ]
}